Hwk1/__init__.py
Hwk1/mynewclass.py
Hwk1-0.1.0.dist-info/METADATA
Hwk1-0.1.0.dist-info/WHEEL
Hwk1-0.1.0.dist-info/top_level.txt
Hwk1-0.1.0.dist-info/RECORD
